{
    "name": "Saudi Arabia",
    "status": "Completed",
    "weekendInfo": {
        "weekendType": "Normal",
        "sessionInfo": {
            "fp1": {
                "time": "2023-03-17T13:30:00Z"
            },
            "fp2": {
                "time": "2023-03-17T17:30:00Z"
            },
            "fp3": {
                "time": "2023-03-19T13:30:00Z"
            },
            "qualifying": {
                "time": "2023-03-18T17:00:00Z"
            },
            "race": {
                "time": "2023-03-19T17:00:00Z"
            }
        }
    },
    "standings": [
        {
            "pos": 1,
            "driverNum": 11,
            "gap": {
                "status": "Leader"
            }
        },
        {
            "pos": 2,
            "driverNum": 1,
            "gap": {
                "status": "SameLapAsLeader",
                "behind": 5.355
            }
        },
        {
            "pos": 3,
            "driverNum": 14,
            "gap": {
                "status": "SameLapAsLeader",
                "behind": 20.728
            }
        }
    ]
}